Workbook

Sheet Summary
A1: Foundation Module — one month of ads at ₹500/day
A2: Budget ₹15,000 · Price ₹4,999 · Prepared August 2026. All figures flow from the Assumptions tab.
B5: Worst case | C5: Realistic | D5: Best case
A6: Ad spend (₹) | B6: =Funnel!B9 -> 15000 | C6: =Funnel!C9 -> 15000 | D6: =Funnel!D9 -> 15000
A7: People reached (impressions) | B7: =Funnel!B10 -> 57692.308 | C7: =Funnel!C10 -> 93750 | D7: =Funnel!D10 -> 136363.64
A8: Clicks to landing page | B8: =Funnel!B11 -> 403.84615 | C8: =Funnel!C11 -> 1125 | D8: =Funnel!D11 -> 2181.8182
A9: Form submissions | B9: =Funnel!B13 -> 4.8461538 | C9: =Funnel!C13 -> 32.4 | D9: =Funnel!D13 -> 87.272727
A10: Enrolments | B10: =Funnel!B14 -> 0.33923077 | C10: =Funnel!C14 -> 5.184 | D10: =Funnel!D14 -> 19.2
A11: Revenue (₹) | B11: =Funnel!B18 -> 1695.8146 | C11: =Funnel!C18 -> 25914.816 | D11: =Funnel!D18 -> 95980.8
A12: Net before other costs (₹) | B12: =Funnel!B20 -> -13304.185 | C12: =Funnel!C20 -> 10914.816 | D12: =Funnel!D20 -> 80980.8
A13: ROAS | B13: =Funnel!B21 -> 0.11305431 | C13: =Funnel!C21 -> 1.7276544 | D13: =Funnel!D21 -> 6.39872
A14: Cost per enrolment (₹) | B14: =Funnel!B22 -> 44217.687 | C14: =Funnel!C22 -> 2893.5185 | D14: =Funnel!D22 -> 781.25
A17: THE ONE NUMBER THAT MATTERS
A18: Enrolments needed just to cover the ad spend | B18: =BreakEven!B8 -> 4
A19: Four students. Three would leave you ₹3 short — ₹4,999 × 3 = ₹14,997 against ₹15,000 of spend. Everything above four is profit on the ad line. In the realistic case you clear that bar by about one student, which is a very thin margin, and it is why the landing page matters more than the ads do.
A22: WHAT THIS MODEL ACTUALLY SAYS
A23: ▪ ₹500/day is a test budget, not a growth budget.
A24: A month at this level produces roughly five enrolments in the realistic case. That is enough to learn whether the funnel works. It is not enough to fill a batch.
A26: ▪ The downside is capped and small; the upside is real.
A27: Worst case you lose about ₹13,000 — roughly the cost of one enrolment. Best case you make about ₹80,000. That is a sensible risk to take, and it is the strongest argument for running this at all.
A29: ▪ The campaign will never exit Meta's learning phase at this budget.
A30: Meta wants ~50 conversions per week per ad set. You will produce about one. Optimise for landing page views or form starts instead of purchases, or the algorithm is flying blind.
A32: ▪ Your biggest lever is the landing page, not the ads.
A33: Payment completion rate moves the outcome more than CTR does. Going from 16% to 22% checkout completion is worth more than doubling your click rate — and it costs nothing but a page edit.
A35: ▪ Non-refundable is probably costing you the most.
A36: It sits exactly where the money is won or lost. A short refund window would likely pay for itself several times over at this price point on cold traffic.
... A46: Assumptions — change anything blue/yellow. · Funnel — the full calculation. · BreakEven — sensitivity grid and the learning-phase problem. · ScaleUp — what more budget buys. · Benchmarks — sources for every published figure used.

Sheet Assumptions
A1: Assumptions — edit the blue cells
A2: Every number in this workbook is driven from this sheet. Change anything blue and all scenarios recalculate.
A4: CAMPAIGN INPUTS
A5: Daily budget (₹) | B5: 500 | E5: From you. Meta charges per day; a month is billed as 30 daily cycles.
A6: Campaign length (days) | B6: 30 | E6: One month.
A7: Price per enrolment (₹) | B7: 4999 | E7: Foundation Module campaign price, from your landing page.
A8: Standard price (₹) | B8: 29999 | E8: Anchor price shown on the landing page. Not used in revenue maths.
A9: Total ad spend for the month (₹) | B9: =B5*B6 -> 15000 | E9: Daily budget × days.
A12: SCENARIO DRIVERS
A13: Three cases. These five rates are what actually decide whether this campaign makes or loses money.
A15: Funnel rate | B15: Worst case | C15: Realistic | D15: Best case | E15: Where the number comes from
A16: CPM — cost per 1,000 impressions (₹) | B16: 260 | C16: 160 | D16: 110 | E16: India Meta CPM benchmarks 2026 run ₹50–400; education auctions are crowded and rose ~15% this year. A narrow pharma-student audience prices above broad. Reels placement is 25–40% cheaper than feed, which is why the best case is achievable.
A17: CTR — link click rate | B17: 0.007 | C17: 0.012 | D17: 0.016 | E17: Meta global average ~0.9%. Above 1.2% indicates above-average creative. Below 0.8% on cold traffic signals a creative problem, not an audience problem.
A18: Landing page view rate | B18: 0.6 | C18: 0.72 | D18: 0.8 | E18: Share of clicks that actually load the page. Losses come from slow mobile loads and accidental taps. Judgement estimate — measure and replace with your real number.
A19: Form submission rate | B19: 0.02 | C19: 0.04 | D19: 0.05 | E19: Share of page visitors who complete the form. Gated behind a visible ₹4,999 price, so lower than a free lead magnet. Judgement estimate.
A20: Payment completion rate | B20: 0.07 | C20: 0.16 | D20: 0.22 | E20: Share of form submissions that finish Razorpay checkout. Non-refundable at ₹4,999 on cold traffic is the main drag here. Judgement estimate — this is the single most uncertain input in the model.
A23: A NOTE ON HOW THESE WERE SET
A24: • CPM and CTR are anchored to published India Meta benchmarks for 2026 (sources on the Benchmarks tab).
A25: • The three page-and-checkout rates are judgement estimates. Nobody publishes reliable benchmarks for "cold traffic to a non-refundable ₹4,999 checkout" because very few people run that funnel.
A26: • The best case is deliberately NOT every input at its most optimistic. Compounding five best cases produces a fantasy — it implies a cost per form-fill far below anything the India education benchmarks support. Best case here means "this went well", not "everything went perfectly".
A27: • Replace all five with your real numbers after week one. The model is built to be overwritten.

Sheet Funnel
A1: Funnel model — one month at ₹500/day
A2: Black cells are formulas driven from the Assumptions tab. Nothing here is typed in by hand.
A5: Stage | B5: Worst case | C5: Realistic | D5: Best case | E5: What this step means
A9: Ad spend (₹) | B9: =Assumptions!$B$9 -> 15000 | C9: =Assumptions!$B$9 -> 15000 | D9: =Assumptions!$B$9 -> 15000 | E9: Same in all three cases — the budget is fixed.
A10: Impressions | B10: =B9/Assumptions!B16*1000 -> 57692.308 | C10: =C9/Assumptions!C16*1000 -> 93750 | D10: =D9/Assumptions!D16*1000 -> 136363.64 | E10: Times your ad appears on a screen. Spend ÷ CPM × 1,000.
A11: Link clicks | B11: =B10*Assumptions!B17 -> 403.84615 | C11: =C10*Assumptions!C17 -> 1125 | D11: =D10*Assumptions!D17 -> 2181.8182 | E11: People who tapped through to the landing page.
A12: Landing page views | B12: =B11*Assumptions!B18 -> 242.30769 | C12: =C11*Assumptions!C18 -> 810 | D12: =D11*Assumptions!D18 -> 1745.4545 | E12: Clicks that actually loaded the page.
A13: Form submissions | B13: =B12*Assumptions!B19 -> 4.8461538 | C13: =C12*Assumptions!C19 -> 32.4 | D13: =D12*Assumptions!D19 -> 87.272727 | E13: People who filled in their details.
A14: Enrolments (paid) | B14: =B13*Assumptions!B20 -> 0.33923077 | C14: =C13*Assumptions!C20 -> 5.184 | D14: =D13*Assumptions!D20 -> 19.2 | E14: People who completed the Razorpay payment. This is the only number that pays the bills.
A16: MONEY
B17: Worst case | C17: Realistic | D17: Best case | E17: Notes
A18: Revenue (₹) | B18: =B14*Assumptions!$B$7 -> 1695.8146 | C18: =C14*Assumptions!$B$7 -> 25914.816 | D18: =D14*Assumptions!$B$7 -> 95980.8 | E18: Enrolments × ₹4,999. Gross — before Razorpay fees, taxes and delivery cost.
A19: Ad spend (₹) | B19: =-Assumptions!$B$9 -> -15000 | C19: =-Assumptions!$B$9 -> -15000 | D19: =-Assumptions!$B$9 -> -15000
A20: Net before other costs (₹) | B20: =B18+B19 -> -13304.185 | C20: =C18+C19 -> 10914.816 | D20: =D18+D19 -> 80980.8 | E20: Revenue minus ad spend only. Your own time, Razorpay fees (~2%) and GST are NOT in here.
A21: ROAS (return on ad spend) | B21: =IF(Assumptions!$B$9=0,0,B18/Assumptions!$B$9) -> 0.11305431 | C21: =IF(Assumptions!$B$9=0,0,C18/Assumptions!$B$9) -> 1.7276544 | D21: =IF(Assumptions!$B$9=0,0,D18/Assumptions!$B$9) -> 6.39872 | E21: Revenue per ₹1 of ad spend. Below 1.00x means the ads lost money.
A22: CAC — cost per enrolment (₹) | B22: =IF(B14=0,0,Assumptions!$B$9/B14) -> 44217.687 | C22: =IF(C14=0,0,Assumptions!$B$9/C14) -> 2893.5185 | D22: =IF(D14=0,0,Assumptions!$B$9/D14) -> 781.25 | E22: What one paying student costs you. Must stay comfortably under ₹4,999.
A23: Cost per form submission (₹) | B23: =IF(B13=0,0,Assumptions!$B$9/B13) -> 3095.2381 | C23: =IF(C13=0,0,Assumptions!$B$9/C13) -> 462.96296 | D23: =IF(D13=0,0,Assumptions!$B$9/D13) -> 171.875 | E23: Compare against the India education benchmark of ₹180–400 per lead. Ours sits higher because the form is behind a visible price.

Sheet BreakEven
A1: Break-even and sensitivity
A2: The question that matters more than any scenario: how many students do you need before the ads stop costing you money?
A4: BREAK-EVEN
A5: Total ad spend for the month (₹) | B5: =Assumptions!$B$9 -> 15000
A6: Price per enrolment (₹) | B6: =Assumptions!$B$7 -> 4999
A7: Enrolments needed to break even | B7: =B5/B6 -> 3.0006001
A8: Round up — students you must actually get | B8: =ROUNDUP(B7,0) -> 4
A10: Break-even counts ad spend only. Add Razorpay fees (~2%), GST, and the cost of actually delivering the programme and the real figure is higher.
A13: SENSITIVITY — ENROLMENTS AT DIFFERENT CTR AND PAYMENT RATES
A14: Realistic CPM, landing page rate and form rate held constant. Only the two levers you can most easily influence are varied: creative quality (CTR) and checkout friction (payment completion).
A16: CTR ↓ Payment completion → | B16: 0.06 | C16: 0.1 | D16: 0.14 | E16: 0.18 | F16: 0.22 | G16: 0.26
A17: 0.006 | B17: =Assumptions!$B$9/Assumptions!$C$16*1000*$A17*Assumptions!$C$18*Assumptions!$C$19*B$16 -> 0.972 | C17: =Assumptions!$B$9/Assumptions!$C$16*1000*$A17*Assumptions!$C$18*Assumptions!$C$19*C$16 -> 1.62 | D17: =Assumptions!$B$9/Assumptions!$C$16*1000*$A17*Assumptions!$C$18*Assumptions!$C$19*D$16 -> 2.268 | E17: =Assumptions!$B$9/Assumptions!$C$16*1000*$A17*Assumptions!$C$18*Assumptions!$C$19*E$16 -> 2.916 | F17: =Assumptions!$B$9/Assumptions!$C$16*1000*$A17*Assumptions!$C$18*Assumptions!$C$19*F$16 -> 3.564 | G17: =Assumptions!$B$9/Assumptions!$C$16*1000*$A17*Assumptions!$C$18*Assumptions!$C$19*G$16 -> 4.212
A18: 0.008 | B18: =Assumptions!$B$9/Assumptions!$C$16*1000*$A18*Assumptions!$C$18*Assumptions!$C$19*B$16 -> 1.296 | C18: =Assumptions!$B$9/Assumptions!$C$16*1000*$A18*Assumptions!$C$18*Assumptions!$C$19*C$16 -> 2.16 | D18: =Assumptions!$B$9/Assumptions!$C$16*1000*$A18*Assumptions!$C$18*Assumptions!$C$19*D$16 -> 3.024 | E18: =Assumptions!$B$9/Assumptions!$C$16*1000*$A18*Assumptions!$C$18*Assumptions!$C$19*E$16 -> 3.888 | F18: =Assumptions!$B$9/Assumptions!$C$16*1000*$A18*Assumptions!$C$18*Assumptions!$C$19*F$16 -> 4.752 | G18: =Assumptions!$B$9/Assumptions!$C$16*1000*$A18*Assumptions!$C$18*Assumptions!$C$19*G$16 -> 5.616
A19: 0.01 | B19: =Assumptions!$B$9/Assumptions!$C$16*1000*$A19*Assumptions!$C$18*Assumptions!$C$19*B$16 -> 1.62 | C19: =Assumptions!$B$9/Assumptions!$C$16*1000*$A19*Assumptions!$C$18*Assumptions!$C$19*C$16 -> 2.7 | D19: =Assumptions!$B$9/Assumptions!$C$16*1000*$A19*Assumptions!$C$18*Assumptions!$C$19*D$16 -> 3.78 | E19: =Assumptions!$B$9/Assumptions!$C$16*1000*$A19*Assumptions!$C$18*Assumptions!$C$19*E$16 -> 4.86 | F19: =Assumptions!$B$9/Assumptions!$C$16*1000*$A19*Assumptions!$C$18*Assumptions!$C$19*F$16 -> 5.94 | G19: =Assumptions!$B$9/Assumptions!$C$16*1000*$A19*Assumptions!$C$18*Assumptions!$C$19*G$16 -> 7.02
A20: 0.012 | B20: =Assumptions!$B$9/Assumptions!$C$16*1000*$A20*Assumptions!$C$18*Assumptions!$C$19*B$16 -> 1.944 | C20: =Assumptions!$B$9/Assumptions!$C$16*1000*$A20*Assumptions!$C$18*Assumptions!$C$19*C$16 -> 3.24 | D20: =Assumptions!$B$9/Assumptions!$C$16*1000*$A20*Assumptions!$C$18*Assumptions!$C$19*D$16 -> 4.536 | E20: =Assumptions!$B$9/Assumptions!$C$16*1000*$A20*Assumptions!$C$18*Assumptions!$C$19*E$16 -> 5.832 | F20: =Assumptions!$B$9/Assumptions!$C$16*1000*$A20*Assumptions!$C$18*Assumptions!$C$19*F$16 -> 7.128 | G20: =Assumptions!$B$9/Assumptions!$C$16*1000*$A20*Assumptions!$C$18*Assumptions!$C$19*G$16 -> 8.424
A21: 0.014 | B21: =Assumptions!$B$9/Assumptions!$C$16*1000*$A21*Assumptions!$C$18*Assumptions!$C$19*B$16 -> 2.268 | C21: =Assumptions!$B$9/Assumptions!$C$16*1000*$A21*Assumptions!$C$18*Assumptions!$C$19*C$16 -> 3.78 | D21: =Assumptions!$B$9/Assumptions!$C$16*1000*$A21*Assumptions!$C$18*Assumptions!$C$19*D$16 -> 5.292 | E21: =Assumptions!$B$9/Assumptions!$C$16*1000*$A21*Assumptions!$C$18*Assumptions!$C$19*E$16 -> 6.804 | F21: =Assumptions!$B$9/Assumptions!$C$16*1000*$A21*Assumptions!$C$18*Assumptions!$C$19*F$16 -> 8.316 | G21: =Assumptions!$B$9/Assumptions!$C$16*1000*$A21*Assumptions!$C$18*Assumptions!$C$19*G$16 -> 9.828
A22: 0.016 | B22: =Assumptions!$B$9/Assumptions!$C$16*1000*$A22*Assumptions!$C$18*Assumptions!$C$19*B$16 -> 2.592 | C22: =Assumptions!$B$9/Assumptions!$C$16*1000*$A22*Assumptions!$C$18*Assumptions!$C$19*C$16 -> 4.32 | D22: =Assumptions!$B$9/Assumptions!$C$16*1000*$A22*Assumptions!$C$18*Assumptions!$C$19*D$16 -> 6.048 | E22: =Assumptions!$B$9/Assumptions!$C$16*1000*$A22*Assumptions!$C$18*Assumptions!$C$19*E$16 -> 7.776 | F22: =Assumptions!$B$9/Assumptions!$C$16*1000*$A22*Assumptions!$C$18*Assumptions!$C$19*F$16 -> 9.504 | G22: =Assumptions!$B$9/Assumptions!$C$16*1000*$A22*Assumptions!$C$18*Assumptions!$C$19*G$16 -> 11.232
A23: 0.02 | B23: =Assumptions!$B$9/Assumptions!$C$16*1000*$A23*Assumptions!$C$18*Assumptions!$C$19*B$16 -> 3.24 | C23: =Assumptions!$B$9/Assumptions!$C$16*1000*$A23*Assumptions!$C$18*Assumptions!$C$19*C$16 -> 5.4 | D23: =Assumptions!$B$9/Assumptions!$C$16*1000*$A23*Assumptions!$C$18*Assumptions!$C$19*D$16 -> 7.56 | E23: =Assumptions!$B$9/Assumptions!$C$16*1000*$A23*Assumptions!$C$18*Assumptions!$C$19*E$16 -> 9.72 | F23: =Assumptions!$B$9/Assumptions!$C$16*1000*$A23*Assumptions!$C$18*Assumptions!$C$19*F$16 -> 11.88 | G23: =Assumptions!$B$9/Assumptions!$C$16*1000*$A23*Assumptions!$C$18*Assumptions!$C$19*G$16 -> 14.04
A25: Break-even line
A26: Any cell in the grid at or above the break-even number in B8 means the campaign paid for itself. Below it, you funded Meta.
A29: THE STRUCTURAL PROBLEM WITH ₹500/DAY
A30: • Meta needs roughly 50 conversions per week, per ad set, to exit the learning phase and optimise properly.
A31: • At the realistic case this campaign produces about 5 purchases in a MONTH — roughly one a week. The algorithm will never leave the learning phase, so it never learns who buys.
A32: • Practical fix: do not optimise the campaign for Purchase. Optimise for a cheaper mid-funnel event — landing page view, or form start — which happens often enough to train on. Then watch purchases as your reporting metric, not your optimisation target.
A33: • Second consequence: at this volume a single week of data tells you almost nothing. Two enrolments versus four is noise, not a signal. Resist the urge to switch off a script on day three.

Sheet ScaleUp
A1: What happens if you spend more
A2: Realistic-case rates held constant, except CPM — which rises as you push the same creative at a bigger audience.
B5: ₹500/day | C5: ₹1,500/day | D5: ₹3,000/day
A6: Daily budget (₹) | B6: 500 | C6: 1500 | D6: 3000
A7: Monthly spend (₹) | B7: =B6*Assumptions!$B$6 -> 15000 | C7: =C6*Assumptions!$B$6 -> 45000 | D7: =D6*Assumptions!$B$6 -> 90000
A8: CPM assumption (₹) | B8: 160 | C8: 185 | D8: 225
F9: CPM rises with budget because you exhaust the cheapest slice of the audience first and frequency climbs. The 15% and 40% increases used here are judgement estimates, not published figures.
A10: Impressions | B10: =B7/B8*1000 -> 93750 | C10: =C7/C8*1000 -> 243243.24 | D10: =D7/D8*1000 -> 400000
A11: Link clicks | B11: =B10*Assumptions!$C$17 -> 1125 | C11: =C10*Assumptions!$C$17 -> 2918.9189 | D11: =D10*Assumptions!$C$17 -> 4800
A12: Landing page views | B12: =B11*Assumptions!$C$18 -> 810 | C12: =C11*Assumptions!$C$18 -> 2101.6216 | D12: =D11*Assumptions!$C$18 -> 3456
A13: Form submissions | B13: =B12*Assumptions!$C$19 -> 32.4 | C13: =C12*Assumptions!$C$19 -> 84.064865 | D13: =D12*Assumptions!$C$19 -> 138.24
A14: Enrolments | B14: =B13*Assumptions!$C$20 -> 5.184 | C14: =C13*Assumptions!$C$20 -> 13.450378 | D14: =D13*Assumptions!$C$20 -> 22.1184
A15: Revenue (₹) | B15: =B14*Assumptions!$B$7 -> 25914.816 | C15: =C14*Assumptions!$B$7 -> 67238.442 | D15: =D14*Assumptions!$B$7 -> 110569.88
A16: Net before other costs (₹) | B16: =B15-B7 -> 10914.816 | C16: =C15-C7 -> 22238.442 | D16: =D15-D7 -> 20569.882
A17: ROAS | B17: =IF(B7=0,0,B15/B7) -> 1.7276544 | C17: =IF(C7=0,0,C15/C7) -> 1.4941876 | D17: =IF(D7=0,0,D15/D7) -> 1.2285542
A18: CAC per enrolment (₹) | B18: =IF(B14=0,0,B7/B14) -> 2893.5185 | C18: =IF(C14=0,0,C7/C14) -> 3345.6308 | D18: =IF(D14=0,0,D7/D14) -> 4069.0104
A21: HOW TO READ THIS
A22: • Look at the Net row, not the Revenue row. Revenue keeps climbing with budget — but net profit peaks around ₹1,500/day and then FALLS at ₹3,000/day, because CPM rises faster than revenue does. Spending more money here earns you less. That is the single most useful thing on this sheet.
A23: • Do not jump to ₹3,000/day because the revenue column looks better. These numbers assume the realistic conversion rates hold at scale — and they usually do not, because a bigger audience is a colder audience.
A24: • The correct sequence is: prove CAC at ₹500/day, then raise budget by roughly 30% every three days while CAC stays under about ₹2,000. If CAC climbs past that, stop and fix the page before spending more.
A25: • One genuine advantage of scale: at ₹3,000/day you produce enough purchases per week for Meta to actually optimise, which tends to improve efficiency rather than worsen it. That effect is not modelled here — treat these figures as the pessimistic view of scaling.

Sheet Benchmarks
A1: Benchmarks and sources
A2: Where the published numbers came from, and which numbers are judgement rather than data.
A5: Metric | B5: Published range | C5: What it means for us | D5: Source
A6: Meta CPM, India (all industries) | B6: ₹50–400 (Facebook) ₹45–350 (Instagram) | C6: Wide because it spans every industry and audience size. Our narrow pharma-student audience prices in the middle-to-upper part of the range. | D6: productgrowth.in / vgraple.com, India Meta benchmarks 2026
A7: Meta CPM, India — trend | B7: Up ~23% year on year | C7: Rising costs, concentrated in tier-1 metros. Targeting tier-2 and tier-3 cities can cut CPM by 30–50% — worth testing given our audience is students. | D7: productgrowth.in, aggregated from 340+ Indian accounts, Jan–Mar 2026
A8: Education sector cost trend | B8: Up ~15% in 2026 | C8: Crowded auctions in education specifically. Factored into our CPM assumptions. | D8: upgrowth.in, Facebook Ads pricing by industry 2026
A9: Reels vs feed placement | B9: Reels 25–40% cheaper CPM | C9: Directly relevant — our creative is vertical video. This is the main reason the best-case CPM of ₹110 is realistic. | D9: productgrowth.in, India Meta benchmarks 2026
A10: CTR, Meta global average | B10: ~0.9% | C10: Above 1.2% means above-average creative. Below 0.8% on cold traffic points to a creative problem, not an audience problem. | D10: owlclaw.com / adlibrary.com, Meta benchmarks 2026
A11: Cost per lead, India education/edtech | B11: ₹180–400 | C11: Our cost per form submission should be compared against this. Ours will run higher because the form sits behind a visible ₹4,999 price rather than a free offer. | D11: upgrowth.in / paidmediaworld.com, India 2026
A12: CPC, India education campaigns | B12: ₹8–15 | C12: Useful cross-check. Our realistic case implies a CPC in this band, which suggests the assumptions are not wildly off. | D12: superads.ai / vgraple.com, India benchmarks
A14: NUMBERS THAT ARE JUDGEMENT, NOT DATA
A15: Three inputs in this model have no reliable published benchmark, because almost nobody runs cold paid traffic straight to a non-refundable ₹4,999 checkout. They are informed estimates and should be replaced with your own measurements as soon as week one data exists:
A16: • Landing page view rate
A17: • Form submission rate
A18: • Payment completion rate
A20: Of the three, payment completion rate carries by far the most uncertainty and the most impact. If any single number in this workbook turns out to be wrong, it will be that one.
